haros_plugin_pbt_gen/__init__.py
haros_plugin_pbt_gen/data.py
haros_plugin_pbt_gen/events.py
haros_plugin_pbt_gen/hypothesis_ast.py
haros_plugin_pbt_gen/plugin.py
haros_plugin_pbt_gen/plugin.yaml
haros_plugin_pbt_gen/selectors.py
haros_plugin_pbt_gen/test_runner.py
haros_plugin_pbt_gen/util.py
haros_plugin_pbt_gen/templates/base_strategies.py
haros_plugin_pbt_gen/templates/custom_msg_strategies.python.jinja
haros_plugin_pbt_gen/templates/default_msg_strategies.python.jinja
haros_plugin_pbt_gen/templates/eval.python.jinja
haros_plugin_pbt_gen/templates/rv_common.python.jinja
haros_plugin_pbt_gen/templates/test_case.python.jinja
haros_plugin_pbt_gen/templates/test_script.python.jinja
haros_plugin_pbt_gen/templates/trace_absence.python.jinja
haros_plugin_pbt_gen/templates/trace_common.python.jinja
haros_plugin_pbt_gen/templates/trace_existence.python.jinja
haros_plugin_pbt_gen/templates/trace_precedence.python.jinja
haros_plugin_pbt_gen/templates/trace_prevention.python.jinja
haros_plugin_pbt_gen/templates/trace_response.python.jinja
haros_plugin_pbt_gen/templates/unused.python.jinja
haros_plugin_pbt_gen-0.4.0.dist-info/LICENSE
haros_plugin_pbt_gen-0.4.0.dist-info/METADATA
haros_plugin_pbt_gen-0.4.0.dist-info/WHEEL
haros_plugin_pbt_gen-0.4.0.dist-info/top_level.txt
haros_plugin_pbt_gen-0.4.0.dist-info/RECORD
